CHANGELOG.rst
LICENCE.rst
aleksis/apps/paweljong/__init__.py
aleksis/apps/paweljong/apps.py
aleksis/apps/paweljong/data_checks.py
aleksis/apps/paweljong/filters.py
aleksis/apps/paweljong/forms.py
aleksis/apps/paweljong/locale/.keepdir
aleksis/apps/paweljong/locale/de_DE/LC_MESSAGES/django.mo
aleksis/apps/paweljong/locale/de_DE/LC_MESSAGES/django.po
aleksis/apps/paweljong/menus.py
aleksis/apps/paweljong/migrations/0001_initial.py
aleksis/apps/paweljong/migrations/0002_event_website.py
aleksis/apps/paweljong/migrations/0003_alter_event_feedback_aspects.py
aleksis/apps/paweljong/migrations/0004_richtext_field_information.py
aleksis/apps/paweljong/migrations/0005_eventregistration_medical_information.py
aleksis/apps/paweljong/migrations/0006_unique_constraints.py
aleksis/apps/paweljong/migrations/0007_terms.py
aleksis/apps/paweljong/migrations/0008_remove_terms_from_event.py
aleksis/apps/paweljong/migrations/0009_remove_feedback.py
aleksis/apps/paweljong/migrations/0010_term_confirmation_text.py
aleksis/apps/paweljong/migrations/0011_registration_accepted_terms.py
aleksis/apps/paweljong/migrations/0012_event_slug.py
aleksis/apps/paweljong/migrations/0013_info_mailings.py
aleksis/apps/paweljong/migrations/0014_move_sent_to_to_through.py
aleksis/apps/paweljong/migrations/0015_registrationstate.py
aleksis/apps/paweljong/migrations/0016_eventregistration_states.py
aleksis/apps/paweljong/migrations/0017_fix_voucher_max_length.py
aleksis/apps/paweljong/migrations/0018_payment_with_tezor.py
aleksis/apps/paweljong/migrations/__init__.py
aleksis/apps/paweljong/models.py
aleksis/apps/paweljong/predicates.py
aleksis/apps/paweljong/preferences.py
aleksis/apps/paweljong/rules.py
aleksis/apps/paweljong/settings.py
aleksis/apps/paweljong/static/css/paweljong.css
aleksis/apps/paweljong/tables.py
aleksis/apps/paweljong/tasks.py
aleksis/apps/paweljong/templates/paweljong/account_wizard.html
aleksis/apps/paweljong/templates/paweljong/event/create.html
aleksis_app_paweljong-1.5.dist-info/entry_points.txt
aleksis_app_paweljong-1.5.dist-info/WHEEL
aleksis_app_paweljong-1.5.dist-info/METADATA
aleksis_app_paweljong-1.5.dist-info/RECORD
