Metadata-Version: 2.1
Name: aleksis-app-paweljong
Version: 1.5
Summary: AlekSIS (School Information System) — App Paweljong (Camp/Event management)
Home-page: https://hacknfun.camp
License: EUPL-1.2-or-later
Author: Tom Teichler
Author-email: tom.teichler@teckids.org
Requires-Python: >=3.9,<4.0
Classifier: Environment :: Web Environment
Classifier: Intended Audience :: Education
Classifier: License :: Other/Proprietary License
Classifier: Programming Language :: Python :: 3
Classifier: Programming Language :: Python :: 3.9
Classifier: Topic :: Education
Requires-Dist: aleksis-app-postbuero (==1.0+20220218233830.a212f707)
Requires-Dist: aleksis-app-tezor (>=1.0,<2.0)
Requires-Dist: aleksis-core (>=2.8.1,<3.0.0)
Requires-Dist: django-formtools (>=2.3,<3.0)
Requires-Dist: django-iban-field (>=0.8,<0.9)
Requires-Dist: django-starfield (>=1.0,<2.0)
Project-URL: Repository, https://edugit.org/Teckids/hacknfun/AlekSIS-App-Paweljong
